[
  {
    "id": "phy_hsc_a69e16_0",
    "question": "জগতে মৌলিক বলের সংখ্যা কয়টি?",
    "options": [
      "২টি",
      "৪টি",
      "৫টি",
      "৬টি"
    ],
    "correctIndex": 1,
    "explanation": "মৌলিক বল মোট ৪টি। যথাক্রমে: মহাকর্ষ বল, তড়িৎচৌম্বক বল, দুর্বল নিউক্লীয় বল ও সবল নিউক্লীয় বল।"
  },
  {
    "id": "phy_hsc_3x3di3_1",
    "question": "ঘর্ষণ বল কোন বলের অন্তর্গত?",
    "options": [
      "মহাকর্ষ",
      "দুর্বল নিউক্লীয় বল",
      "তড়িৎচৌম্বক বল",
      "সবল নিউক্লীয় বল"
    ],
    "correctIndex": 2,
    "explanation": "স্পর্শ বলসমূহ (যেমন: ঘর্ষণ বল, স্প্রিং বল, সান্দ্র বল) মূলত আণবিক পর্যায়ে ইলেকট্রনগুলোর মধ্যকার তড়িৎচৌম্বক বলের পারস্পরিক ক্রিয়ার ফল।"
  },
  {
    "id": "phy_hsc_xpcndu_2",
    "question": "বস্তুর যে ভর ত্বরণ সৃষ্টিতে বাধা দেয় তাকে কী বলে?",
    "options": [
      "মহাকর্ষীয় ভর",
      "ভর ভ্রামক",
      "জড়তা",
      "জাড্য ভর"
    ],
    "correctIndex": 2,
    "explanation": "বস্তু যে অবস্থায় আছে সেই অবস্থায় থাকতে চাওয়ার যে প্রবণতা বা ধর্ম তাকে জড়তা বলে। আবার কোনো বস্তু তার অবস্থার পরিবর্তনে বাধা দেওয়ার পরিমাপই হচ্ছে ভর; অর্থাৎ বস্তুর যে ভর ত্বরণ সৃষ্টিতে বাধা দেয় তাকে জড়তা (বা জাড্য ভর) বলে।"
  },
  {
    "id": "phy_hsc_eryo3w_3",
    "question": "বস্তুর গতি জড়তা কোনটির সমানুপাতিক?",
    "options": [
      "ভর",
      "বেগ",
      "ভরবেগ",
      "বল"
    ],
    "correctIndex": 2,
    "explanation": "জড়তার পরিমাপ হলো ভর। তবে গতিশীল বস্তুর ক্ষেত্রে গতি জড়তা গতিশীল অবস্থার ওপর নির্ভর করে ক্রিয়া করে, যা তার ভরবেগের সাথে সরাসরি সম্পর্কিত।"
  },
  {
    "id": "phy_hsc_hr4cm5_4",
    "question": "নিউক্লিয় বিটা ক্ষয়ের জন্য দায়ী মৌলিক বল কোনটি?",
    "options": [
      "মহাকর্ষ বল",
      "তড়িৎ চৌম্বক বল",
      "সবল নিউক্লীয় বল",
      "দুর্বল নিউক্লীয় বল"
    ],
    "correctIndex": 3,
    "explanation": "দুর্বল নিউক্লীয় বলের পাল্লা অত্যন্ত কম (10⁻¹⁶ m) এবং এটি নিউক্লিয়াসের অভ্যন্তরে বিটা ক্ষয় (β-decay) এবং তেজস্ক্রিয় ভাঙনের জন্য দায়ী।"
  },
  {
    "id": "phy_hsc_hzu2n3_5",
    "question": "দুর্বল নিউক্লীয় বলের জন্য দায়ী কোন কণা?",
    "options": [
      "মেসন",
      "গ্রাভিটন",
      "ফোটন",
      "বোসন"
    ],
    "correctIndex": 3,
    "explanation": "মৌলিক বলসমূহের বিনিময়কারী কণাগুলো হলো: মহাকর্ষ -> গ্রাভিটন; তড়িৎচৌম্বক -> ফোটন; সবল নিউক্লীয় -> মেসন/গ্লুয়ন; দুর্বল নিউক্লীয় -> ডব্লিউ ও জেড বোসন (W & Z Boson)।"
  },
  {
    "id": "phy_hsc_nzu8u0_6",
    "question": "নিচের কোন মৌলিক বলের পাল্লা সবচেয়ে কম?",
    "options": [
      "মহাকর্ষ বল",
      "তড়িৎচৌম্বক বল",
      "সবল নিউক্লীয় বল",
      "দুর্বল নিউক্লীয় বল"
    ],
    "correctIndex": 3,
    "explanation": "মৌলিক বলগুলোর পাল্লা যথাক্রমে: মহাকর্ষ -> অসীম; তড়িৎচৌম্বক -> অসীম; সবল নিউক্লীয় -> 10⁻¹⁵ m; দুর্বল নিউক্লীয় -> 10⁻¹⁶ m। অতএব দুর্বল নিউক্লীয় বলের পাল্লা সবচেয়ে কম।"
  },
  {
    "id": "phy_hsc_dm4cd5_7",
    "question": "একটি বস্তুর ত্বরণ থাকবে কখন?",
    "options": [
      "বেগ থাকলে",
      "গতিশক্তি থাকলে",
      "বল প্রযুক্ত থাকলে",
      "ভরবেগ থাকলে"
    ],
    "correctIndex": 2,
    "explanation": "নিউটনের গতিসূত্রানুসারে, বস্তুর ওপর বাহ্যিক নিট বল প্রযুক্ত থাকলে অবশ্যই বস্তুর ভরবেগের পরিবর্তন তথা ত্বরণ থাকবে।"
  },
  {
    "id": "phy_hsc_c35ym9_8",
    "question": "কোন ধরনের গতির ক্ষেত্রে বল ও বলের দিকে বস্তুর সরণের মধ্যবর্তী কোণ 0° হয়?",
    "options": [
      "একমাত্রিক গতি",
      "দ্বিমাত্রিক গতি",
      "ত্রিমাত্রিক গতি",
      "বৃত্তাকার গতি"
    ],
    "correctIndex": 0,
    "explanation": "সরলরৈখিক বা একমাত্রিক গতির ক্ষেত্রে বল যেদিকে প্রযুক্ত হয়, সরণও সেই একই সরলরেখা বরাবর ঘটে; ফলে এদের মধ্যবর্তী কোণ 0° হয়।"
  },
  {
    "id": "phy_hsc_kywlsi_9",
    "question": "ফোটন কণা বিনিময়ের মাধ্যমে কোন বল কার্যকর হয়?",
    "options": [
      "মহাকর্ষ",
      "তড়িৎচৌম্বক",
      "সবল নিউক্লীয়",
      "দুর্বল নিউক্লীয়"
    ],
    "correctIndex": 1,
    "explanation": "তড়িৎচৌম্বক বলের (Electromagnetic force) পারস্পরিক আদান-প্রদান ও কার্যকারিতার জন্য দায়ী বিনিময়কারী কণা হলো ফোটন।"
  },
  {
    "id": "phy_hsc_792kt0_10",
    "question": "বস্তুর আণবিক গঠন ও রাসায়নিক বিক্রিয়ার জন্য দায়ী কোন বল?",
    "options": [
      "মহাকর্ষ বল",
      "তড়িৎচৌম্বক বল",
      "সবল নিউক্লীয় বল",
      "দুর্বল নিউক্লীয় বল"
    ],
    "correctIndex": 1,
    "explanation": "পদার্থ ইলেকট্রন, প্রোটন ইত্যাদি আধান দ্বারা গঠিত। পরমাণুর আণবিক ও রাসায়নিক বন্ধন এবং বিভিন্ন বিক্রিয়া মূলত ইলেকট্রন আদান-প্রদানের তড়িৎচৌম্বক বলের কারণে ঘটে।"
  },
  {
    "id": "phy_hsc_j4wz1l_11",
    "question": "ইউরেনিয়াম, থোরিয়াম ইত্যাদি মৌলিক পদার্থের তেজস্ক্রিয় ভাঙন ঘটে কোন বলের কারণে?",
    "options": [
      "তেজস্ক্রিয় বল",
      "তড়িৎ চৌম্বক বল",
      "দুর্বল নিউক্লীয় বল",
      "সবল নিউক্লীয় বল"
    ],
    "correctIndex": 2,
    "explanation": "ভারী নিউক্লিয়াসযুক্ত তেজস্ক্রিয় পদার্থের স্বতঃস্ফূর্ত ভাঙন এবং নিউক্লিয়াস থেকে কণা নির্গমনের পেছনে দুর্বল নিউক্লীয় বল কাজ করে।"
  },
  {
    "id": "phy_hsc_dhdv2v_12",
    "question": "নিচের কোনটি সংরক্ষণশীল বলের উদাহরণ?",
    "options": [
      "ঘর্ষণ বল",
      "সান্দ্র বল",
      "অভিকর্ষীয় বল",
      "ঘাত বল"
    ],
    "correctIndex": 2,
    "explanation": "যে বল দ্বারা কোনো বস্তুকে একটি পূর্ণ চক্র আবর্তন করালে সম্পাদিত কাজের পরিমাণ শূন্য হয়, তাকে সংরক্ষণশীল বল বলে। অভিকর্ষ বল একটি আদর্শ সংরক্ষণশীল বল।"
  },
  {
    "id": "phy_hsc_m85ovd_13",
    "question": "কোন কণার বিনিময়ে নিউক্লীয় সবল বল কাজ করে?",
    "options": [
      "ফোটন",
      "গ্রাভিটন",
      "বোসন",
      "মেসন"
    ],
    "correctIndex": 3,
    "explanation": "সবল নিউক্লীয় বলের জন্য দায়ী বা পারস্পরিক বিনিময়কারী কণা হলো মেসন (বা গ্লুয়ন)।"
  },
  {
    "id": "phy_hsc_so5bq7_14",
    "question": "কোনো একটি বস্তুকে অমসৃণ তলে স্থির অবস্থায় রাখা হলে তার উপর মোট কয়টি বল ক্রিয়া করে?",
    "options": [
      "১",
      "২",
      "৩",
      "৪"
    ],
    "correctIndex": 2,
    "explanation": "বস্তুটি স্থির থাকলে তার ওপর ৩টি বল ক্রিয়া করে: ১. খাড়া নিচের দিকে বস্তুর ওজন, ২. তলের লম্ব প্রতিক্রিয়া বল এবং ৩. তল বরাবর স্থিতি ঘর্ষণ বল যা ওজনের উপাংশকে ভারসাম্যপূর্ণ রাখে।"
  },
  {
    "id": "phy_hsc_g58afj_15",
    "question": "তিনটি সমমানের বল একটি বিন্দুতে ক্রিয়া করে সাম্যাবস্থার সৃষ্টি করলে তাদের অন্তর্ভূক্ত কোণের অনুপাত কত?",
    "options": [
      "60° : 60° : 240°",
      "90° : 90° : 180°",
      "120° : 120° : 120°",
      "150° : 150° : 60°"
    ],
    "correctIndex": 2,
    "explanation": "লামির সূত্রানুসারে, তিনটি সমমানের বল সাম্যাবস্থায় থাকলে প্রতিটি বলের মধ্যবর্তী কোণ সমান হতে হবে। বৃত্তের মোট কোণ 360° হওয়ায় কোণগুলো হবে 360° / 3 = 120° করে, অর্থাৎ অনুপাত 120° : 120° : 120°।"
  },
  {
    "id": "phy_hsc_n9x0tv_16",
    "question": "সাইকেলের বেগ ও চাকার ঘর্ষণের মধ্যবর্তী কোণ কত?",
    "options": [
      "0°",
      "90°",
      "180°",
      "360°"
    ],
    "correctIndex": 2,
    "explanation": "সাইকেলের গতির দিক বা বেগের দিক যেদিকে থাকে, গতিকে বাধা প্রদানকারী ঘর্ষণ বল সর্বদা তার বিপরীত দিকে ক্রিয়া করে। ফলে এদের মধ্যবর্তী কোণ সর্বদা 180° হয়।"
  },
  {
    "id": "phy_hsc_tezyrv_17",
    "question": "তেজস্ক্রিয় ক্ষয়ের বেলায় কোন বল ক্রিয়াশীল?",
    "options": [
      "মহাকর্ষ বল",
      "তড়িৎ চৌম্বক বল",
      "গতিশীল নিউক্লীয় বল",
      "দুর্বল নিউক্লীয় বল"
    ],
    "correctIndex": 3,
    "explanation": "তেজস্ক্রিয় নিউক্লিয়াস থেকে যখন বিটা (β) কণা বা অন্যান্য তেজস্ক্রিয় কণা নির্গত হয়, তখন সেখানে দুর্বল নিউক্লীয় বল ক্রিয়াশীল থাকে।"
  },
  {
    "id": "phy_hsc_wfivx1_0",
    "question": "দুর্বল নিউক্লীয় বলের ক্ষেত্রে কোন উত্তরটি সঠিক?\ni. এই বল অস্থিতিশীল নিউক্লিয়াসের কারণ\nii. এই বলের পাল্লা 10⁻¹⁶ m\niii. এই বলের জন্য দায়ী ফোটন\nনিচের কোনটি সঠিক?",
    "options": [
      "i ও ii",
      "ii ও iii",
      "i ও iii",
      "i, ii ও iii"
    ],
    "correctIndex": 0,
    "explanation": "দুর্বল নিউক্লীয় বল অস্থিতিশীল নিউক্লিয়াসের বিটা ক্ষয়ের কারণ (i) এবং এর পাল্লা 10⁻¹⁶ m (ii)। তবে এই বলের জন্য দায়ী বিনিময়কারী কণা হলো W ও Z বোসন, ফোটন নয় (iii)। অতএব i ও ii সঠিক।"
  },
  {
    "id": "phy_hsc_dsth2w_1",
    "question": "যে বলের কারণে বস্তু বৃত্তাকার পথে ঘোরে সেই বল যদি প্রত্যাহার করে নেওয়া হয় তাহলে বস্তুটি গতিজড়তার কারণে—\ni. স্পর্শক বরাবর ছুটে যাবে\nii. ঐ মুহূর্তে বেগের দিক বরাবর ছুটে যাবে\niii. ব্যাসার্ধ বরাবর কেন্দ্রের দিকে ছুটে যাবে\nনিচের কোনটি সঠিক?",
    "options": [
      "i ও ii",
      "ii ও iii",
      "i ও iii",
      "i, ii ও iii"
    ],
    "correctIndex": 0,
    "explanation": "বৃত্তাকার পথে ঘূর্ণনশীল বস্তুর কেন্দ্রমুখী বল প্রত্যাহার করলে বস্তুটি তার গতিজড়তার কারণে ওই মুহূর্তের বেগের দিক অর্থাৎ বৃত্তের স্পর্শক বরাবর সোজা চলে যায়। ব্যাসার্ধ বরাবর কেন্দ্রের দিকে যাবে না। অতএব i ও ii সঠিক।"
  },
  {
    "id": "phy_hsc_lo2qhe_2",
    "question": "কোনো বস্তুর উপর নীট বল শূন্য হলে স্থির থাকবে—\ni. বেগ\nii. ত্বরণ\niii. গতিশক্তি\nনিচের কোনটি সঠিক?",
    "options": [
      "i ও ii",
      "i ও iii",
      "ii ও iii",
      "i, ii ও iii"
    ],
    "correctIndex": 1,
    "explanation": "নিট বল শূন্য হলে বস্তুটির বেগের কোনো পরিবর্তন হয় না (স্থির বেগ) এবং গতিশক্তিও অপরিবর্তিত বা স্থির থাকে (i ও iii)। তবে ত্বরণ শূন্য হয়ে যায়, ত্বরণ স্থির বা কোনো নির্দিষ্ট মানে ধ্রুব থাকে না।"
  },
  {
    "id": "phy_hsc_r56s88_3",
    "question": "সাঁতার কাটার ভিত্তি হলো নিউটনের—",
    "options": [
      "১ম সূত্র",
      "২য় সূত্র",
      "৩য় সূত্র",
      "৪র্থ সূত্র"
    ],
    "correctIndex": 2,
    "explanation": "সাঁতার কাটার সময় হাত-পা দিয়ে পানির ওপর বল (ক্রিয়া) প্রয়োগ করলে পানিও সাঁতারুর ওপর সমান ও বিপরীতমুখী ধাক্কা (প্রতিক্রিয়া) দেয়, যা নিউটনের ৩য় সূত্রের বাস্তব উদাহরণ।"
  },
  {
    "id": "phy_hsc_7dg5i1_4",
    "question": "ঘড়ির কাঁটার গতি কোন গতির উদাহরণ?",
    "options": [
      "পর্যায়বৃত্ত গতি",
      "স্পন্দন গতি",
      "সরলরৈখিক গতি",
      "আপেক্ষিক গতি"
    ],
    "correctIndex": 0,
    "explanation": "ঘড়ির কাঁটা একটি নির্দিষ্ট সময় পরপর নির্দিষ্ট বিন্দুকে একই দিক থেকে অতিক্রম করে, তাই ঘড়ির কাঁটার গতি একটি আদর্শ পর্যায়বৃত্ত গতি।"
  },
  {
    "id": "phy_hsc_aexczn_5",
    "question": "কোনো বস্তুর উপর লব্ধি বল শূন্য হলে—\ni. সমবেগে চলে\nii. সমত্বরণে চলে\niii. গতিশক্তি পরিবর্তন হয় না\nনিচের কোনটি সঠিক?",
    "options": [
      "i ও ii",
      "i ও iii",
      "ii ও iii",
      "i, ii ও iii"
    ],
    "correctIndex": 1,
    "explanation": "লব্ধি বল F_ = 0 হলে, ma = 0 => a = 0 (ত্বরণ শূন্য)। ত্বরণ শূন্য হলে বস্তু সমবেগে চলে (i) এবং এর গতিশক্তি স্থির থাকে বা পরিবর্তন হয় না (iii)।"
  },
  {
    "id": "phy_hsc_crlf14_6",
    "question": "0.1 kg ভরের একটি স্থির বস্তুর উপর 1 N বল 1 s ক্রিয়া করে।\nবস্তুটির ত্বরণ কত?",
    "options": [
      "0.1 m s⁻²",
      "5 m s⁻²",
      "10 m s⁻²",
      "100 m s⁻²"
    ],
    "correctIndex": 2,
    "explanation": "ত্বরণ a = F / m = 1 N / 0.1 kg = 10 m s⁻²।"
  },
  {
    "id": "phy_hsc_7wt254_7",
    "question": "প্রযুক্ত বল অপসারিত হলে গতিশীল বস্তুটির পরিণতি কী হবে?",
    "options": [
      "থেমে যাবে",
      "সমবেগে চলবে",
      "সমত্বরণে চলবে",
      "সমমন্দনে চলবে"
    ],
    "correctIndex": 1,
    "explanation": "1s পর বল অপসারণ করলে অর্জিত বেগ v = u + at = 0 + 10 × 1 = 10 m s⁻¹। বাহ্যিক বল অপসারিত হওয়ায় নিউটনের ১ম সূত্রানুসারে বস্তুটি এই 10 m s⁻¹ সমবেগে চলতে থাকবে।"
  },
  {
    "id": "phy_hsc_wc5b68_8",
    "question": "বলের ঘাতের একক হচ্ছে—",
    "options": [
      "kg m s⁻¹",
      "kg m s⁻²",
      "kg m² s⁻¹",
      "kg m² s⁻²"
    ],
    "correctIndex": 0,
    "explanation": "বলের ঘাত = বল × সময় = N · s = (kg m s⁻²) × s = kg m s⁻¹।"
  },
  {
    "id": "phy_hsc_w90rxx_9",
    "question": "বলের ঘাত এর ক্ষেত্রে কোনটি সঠিক?",
    "options": [
      "বলের মান কম কিন্তু ক্রিয়াকাল বেশি",
      "বলের মান বেশি কিন্তু ক্রিয়াকাল কম",
      "বলের মান ও ক্রিয়াকাল উভয় কম",
      "বলের মান ও ক্রিয়াকাল উভয় বেশি"
    ],
    "correctIndex": 1,
    "explanation": "খুব অল্প সময়ের জন্য (ক্রিয়াকাল কম) খুব বড় মানের বল (বলের মান বেশি) প্রযুক্ত হলে তাকে ঘাত বল বলে এবং এই বল ও সময়ের গুণফলই হলো বলের ঘাত।"
  },
  {
    "id": "phy_hsc_erd8so_10",
    "question": "10 gm ভরের একটি বল 100 cm s⁻¹ বেগে একটি উলম্ব দেওয়ালে অনুভূমিকভাবে আঘাত করে একই বেগে ফিরে গেলো। দেওয়াল কর্তৃক প্রযুক্ত বলের ঘাত কত dyne-sec?",
    "options": [
      "0",
      "100",
      "1000",
      "2000"
    ],
    "correctIndex": 3,
    "explanation": "বেগের পরিবর্তন Δv = 100 - (-100) = 200 cm s⁻¹। বলের ঘাত = ভরবেগের পরিবর্তন = mΔv = 10 gm × 200 cm s⁻¹ = 2000 dyne-sec।"
  },
  {
    "id": "phy_hsc_coyk4b_11",
    "question": "একটি বস্তুর উপর 600 N বল 1 মিনিট ক্রিয়া করে। ভরবেগের পরিবর্তন কত?",
    "options": [
      "3.6 × 10⁴ kg m s⁻¹",
      "3.6 × 10³ kg m s⁻¹",
      "600 kg m s⁻¹",
      "10 kg m s⁻¹"
    ],
    "correctIndex": 0,
    "explanation": "ভরবেগের পরিবর্তন = বলের ঘাত = F × t = 600 N × (1 × 60 s) = 36000 = 3.6 × 10⁴ kg m s⁻¹।"
  },
  {
    "id": "phy_hsc_bvwpys_12",
    "question": "কোনো বস্তুর উপর প্রযুক্ত বল F(t) = t² + t + 2 হলে, t1 = 1 s হতে t2 = 2s সময়ের মধ্যে প্রযুক্ত বলের ঘাত—",
    "options": [
      "4 N s",
      "5.83 N s",
      "8 N s",
      "12 N s"
    ],
    "correctIndex": 1,
    "explanation": "বলের ঘাত J = ∫[t1 থেকে t2] F(t)dt = ∫[1 থেকে 2] (t² + t + 2)dt = [t³/3 + t²/2 + 2t] লিমিট 1 থেকে 2। মান বসালে পাই, (8/3 + 4/2 + 4) - (1/3 + 1/2 + 2) = (8/3 + 6) - (1/3 + 2.5) = 35/6 ≈ 5.83 N s।"
  },
  {
    "id": "phy_hsc_crub89_13",
    "question": "বলের ঘাত দ্বারা বুঝায়—",
    "options": [
      "টর্ক",
      "জড়তার ভ্রামক",
      "রৈখিক ভরবেগের পরিবর্তন",
      "কৌণিক ভরবেগের পরিবর্তন"
    ],
    "correctIndex": 2,
    "explanation": "নিউটনের ২য় সূত্রানুসারে, F = m(v - u)/t => F × t = m(v - u)। অর্থাৎ বলের ঘাত (F × t) সর্বদা রৈখিক ভরবেগের পরিবর্তনের সমান হয়।"
  }
]